{
  "productDefinitions": {
    "Launch": {
      "fs-web-rrg": {
        "name": "Web RRG"
      },
      "fs-daas-rrg": {
        "name": "DaaS RRG"
      },
      "fs-salesforce-rrg": {
        "name": "Salesforce RRG"
      }
    },
    "Client Acquisition B2B": {
      "fs-client-acquisition-b2b-basic": {
        "name": "Basic"
      },
      "fs-client-acquisition-b2b-advanced": {
        "name": "Advanced"
      },
      "fs-client-acquisition-b2b-daas": {
        "name": "DaaS"
      },
      "fs-client-acquisition-b2b-sf": {
        "name": "Salesforce"
      }
    },
    "Client Acquisition B2C": {
      "fs-client-acquisition-b2c-basic": {
        "name": "Basic"
      },
      "fs-client-acquisition-b2c-advanced": {
        "name": "Advanced"
      },
      "fs-client-acquisition-b2c-daas": {
        "name": "DaaS"
      },
      "fs-client-acquisition-b2c-sf": {
        "name": "Salesforce"
      }
    },
    "Dealmaking & PE": {
      "fs-dealmakingpe-basic": {
        "name": "Basic"
      },
      "fs-dealmakingpe-advanced": {
        "name": "Advanced"
      },
      "fs-dealmakingpe-daas": {
        "name": "DaaS"
      },
      "fs-dealmakingpe-sf": {
        "name": "Salesforce"
      }
    },
    "Fundraising": {
      "fs-fundraising-basic": {
        "name": "Basic"
      },
      "fs-fundraising-advanced": {
        "name": "Advanced"
      },
      "fs-fundraising-daas": {
        "name": "DaaS"
      },
      "fs-fundraising-sf": {
        "name": "Salesforce"
      }
    },
    "Talent": {
      "fs-talent-basic": {
        "name": "Basic"
      },
      "fs-talent-advanced": {
        "name": "Advanced"
      },
      "fs-talent-daas": {
        "name": "DaaS"
      },
      "fs-talent-sf": {
        "name": "Salesforce"
      }
    }
  },
  "salesforceProductDefinition": {
    "fs-web-rrg": {
      "cognitoGroups": [
        "universe-professional",
        "universe-wealth",
        "distribution-altrata-web",
        "package-core",
        "package-exec-insights",
        "package-equity-ma",
        "package-wealth",
        "package-philanthropy"
      ],
      "upsells": [],
      "productDescription": "Lorem ipsum dolor sit amet, consectetur adipiscing elit. Maecenas ut venenatis eros. Etiam purus nisl, fringilla et gravida nec, molestie a mi. Aenean laoreet semper neque, in finibus lacus viverra in. Curabitur venenatis lacus velit, quis rutrum enim elementum bibendum. Vivamus hendrerit elementum pulvinar. Etiam ultrices auctor felis id suscipit. Duis tristique felis non nulla pulvinar sodales. Pellentesque non pharetra metus, et faucibus nunc. Sed semper sapien at lacus posuere facilisis. Mauris volutpat dui non justo pretium, ac sagittis ligula mattis. Vestibulum ullamcorper, ipsum nec gravida placerat, massa nisl feugiat massa, ut rhoncus enim arcu nec augue. Cras sed tellus et est finibus laoreet. Aliquam ullamcorper sapien eget aliquet tincidunt. Nunc et elementum velit. Nunc mattis viverra ornare. Mauris malesuada, risus a pulvinar finibus, erat neque semper neque, sit amet porta mi magna a odio.",
      "sellable": false
    },
    "fs-daas-rrg": {
      "cognitoGroups": [
        "universe-professional",
        "universe-wealth",
        "distribution-datafeed-sftp",
        "distribution-datafeed-s3",
        "distribution-datafeed-snowflake",
        "distribution-matching-api",
        "distribution-matching-sftp",
        "distribution-profile-api",
        "distribution-upds-api",
        "distribution-events-api",
        "distribution-alerts-api",
        "package-core",
        "package-exec-insights",
        "package-equity-ma",
        "package-wealth",
        "package-philanthropy"
      ],
      "upsells": [],
      "productDescription": "TBC",
      "sellable": true
    },
    "fs-salesforce-rrg": {
      "cognitoGroups": [
        "universe-professional",
        "universe-wealth",
        "distribution-app-salesforce",
        "package-core",
        "package-exec-insights",
        "package-equity-ma",
        "package-wealth",
        "package-philanthropy"
      ],
      "upsells": [],
      "productDescription": "TBC",
      "sellable": true
    },
    "fs-client-acquisition-b2b-basic": {
      "cognitoGroups": [
        "universe-professional",
        "distribution-altrata-web",
        "package-core",
        "package-exec-insights"
      ],
      "upsells": [
        "package-equity-ma",
        "package-wealth",
        "package-philanthropy",
        "f-news-alerts",
        "f-radar"
      ],
      "productDescription": "TBC",
      "sellable": false
    },
    "fs-client-acquisition-b2b-advanced": {
      "cognitoGroups": [
        "universe-professional",
        "distribution-altrata-web",
        "package-core",
        "package-exec-insights"
      ],
      "upsells": [
        "universe-wealth",
        "package-equity-ma",
        "package-wealth",
        "package-philanthropy",
        "f-news-alerts",
        "f-radar"
      ],
      "productDescription": "TBC",
      "sellable": false
    },
    "fs-client-acquisition-b2b-daas": {
      "cognitoGroups": [
        "universe-professional",
        "distribution-datafeed-sftp",
        "distribution-datafeed-s3",
        "distribution-datafeed-snowflake",
        "distribution-matching-api",
        "distribution-matching-sftp",
        "distribution-profile-api",
        "distribution-upds-api",
        "package-core",
        "package-exec-insights"
      ],
      "upsells": [
        "universe-wealth",
        "distribution-events-api",
        "distribution-alerts-api",
        "distribution-relationships-api",
        "package-equity-ma",
        "package-wealth",
        "package-philanthropy",
        "f-relationships-1st",
        "f-relationships-2nd",
        "f-pathfinder",
        "f-client-networks",
        "f-news-alerts",
        "f-radar"
      ],
      "productDescription": "TBC",
      "sellable": false
    },
    "fs-client-acquisition-b2b-sf": {
      "cognitoGroups": [
        "universe-professional",
        "distribution-altrata-web",
        "distribution-app-salesforce",
        "package-core",
        "package-exec-insights"
      ],
      "upsells": [
        "universe-wealth",
        "package-equity-ma",
        "package-wealth",
        "package-philanthropy",
        "f-news-alerts"
      ],
      "productDescription": "TBC",
      "sellable": true
    },
    "fs-client-acquisition-b2c-basic": {
      "cognitoGroups": [
        "universe-wealth",
        "distribution-altrata-web",
        "package-core",
        "package-wealth"
      ],
      "upsells": [
        "universe-professional",
        "package-exec-insights",
        "package-equity-ma",
        "package-philanthropy",
        "f-news-alerts",
        "f-radar"
      ],
      "productDescription": "TBC",
      "sellable": false
    },
    "fs-client-acquisition-b2c-advanced": {
      "cognitoGroups": [
        "universe-wealth",
        "distribution-altrata-web",
        "package-core",
        "package-wealth"
      ],
      "upsells": [
        "universe-professional",
        "package-exec-insights",
        "package-equity-ma",
        "package-philanthropy",
        "f-news-alerts",
        "f-radar"
      ],
      "productDescription": "TBC",
      "sellable": false
    },
    "fs-client-acquisition-b2c-daas": {
      "cognitoGroups": [
        "universe-wealth",
        "distribution-datafeed-sftp",
        "distribution-datafeed-s3",
        "distribution-datafeed-snowflake",
        "distribution-matching-api",
        "distribution-matching-sftp",
        "distribution-profile-api",
        "distribution-upds-api",
        "package-core",
        "package-wealth"
      ],
      "upsells": [
        "universe-professional",
        "distribution-events-api",
        "distribution-alerts-api",
        "distribution-relationships-api",
        "package-exec-insights",
        "package-equity-ma",
        "package-philanthropy",
        "f-relationships-1st",
        "f-relationships-2nd",
        "f-pathfinder",
        "f-client-networks",
        "f-news-alerts",
        "f-radar"
      ],
      "productDescription": "TBC",
      "sellable": false
    },
    "fs-client-acquisition-b2c-sf": {
      "cognitoGroups": [
        "universe-wealth",
        "distribution-altrata-web",
        "distribution-app-salesforce",
        "package-core",
        "package-exec-insights",
        "package-wealth"
      ],
      "upsells": [
        "universe-professional",
        "package-equity-ma",
        "package-philanthropy",
        "f-news-alerts"
      ],
      "productDescription": "TBC",
      "sellable": false
    },
    "fs-dealmakingpe-basic": {
      "cognitoGroups": [
        "universe-professional",
        "distribution-altrata-web",
        "package-core",
        "package-exec-insights"
      ],
      "upsells": [
        "universe-wealth",
        "package-equity-ma",
        "package-wealth",
        "package-philanthropy",
        "f-news-alerts",
        "f-radar"
      ],
      "productDescription": "TBC",
      "sellable": false
    },
    "fs-dealmakingpe-advanced": {
      "cognitoGroups": [
        "universe-professional",
        "distribution-altrata-web",
        "package-core",
        "package-exec-insights"
      ],
      "upsells": [
        "universe-wealth",
        "package-equity-ma",
        "package-wealth",
        "package-philanthropy",
        "f-news-alerts",
        "f-radar"
      ],
      "productDescription": "TBC",
      "sellable": false
    },
    "fs-dealmakingpe-daas": {
      "cognitoGroups": [
        "universe-professional",
        "distribution-datafeed-sftp",
        "distribution-datafeed-s3",
        "distribution-datafeed-snowflake",
        "distribution-matching-api",
        "distribution-matching-sftp",
        "distribution-profile-api",
        "distribution-upds-api",
        "package-core",
        "package-exec-insights"
      ],
      "upsells": [
        "universe-wealth",
        "distribution-events-api",
        "distribution-alerts-api",
        "distribution-relationships-api",
        "package-equity-ma",
        "package-wealth",
        "package-philanthropy",
        "f-relationships-1st",
        "f-relationships-2nd",
        "f-pathfinder",
        "f-client-networks",
        "f-news-alerts",
        "f-radar"
      ],
      "productDescription": "TBC",
      "sellable": false
    },
    "fs-dealmakingpe-sf": {
      "cognitoGroups": [
        "universe-professional",
        "distribution-altrata-web",
        "distribution-app-salesforce",
        "package-core",
        "package-exec-insights"
      ],
      "upsells": [
        "universe-wealth",
        "package-equity-ma",
        "package-wealth",
        "package-philanthropy",
        "f-news-alerts"
      ],
      "productDescription": "TBC",
      "sellable": false
    },
    "fs-fundraising-basic": {
      "cognitoGroups": [
        "universe-wealth",
        "distribution-altrata-web",
        "package-core",
        "package-philanthropy"
      ],
      "upsells": [
        "universe-professional",
        "package-exec-insights",
        "package-equity-ma",
        "package-wealth",
        "f-news-alerts",
        "f-radar"
      ],
      "productDescription": "TBC",
      "sellable": false
    },
    "fs-fundraising-advanced": {
      "cognitoGroups": [
        "universe-wealth",
        "distribution-altrata-web",
        "package-core",
        "package-philanthropy"
      ],
      "upsells": [
        "universe-professional",
        "package-exec-insights",
        "package-equity-ma",
        "package-wealth",
        "f-news-alerts",
        "f-radar"
      ],
      "productDescription": "TBC",
      "sellable": false
    },
    "fs-fundraising-daas": {
      "cognitoGroups": [
        "universe-wealth",
        "distribution-datafeed-sftp",
        "distribution-datafeed-s3",
        "distribution-datafeed-snowflake",
        "distribution-matching-api",
        "distribution-matching-sftp",
        "distribution-profile-api",
        "distribution-upds-api",
        "package-core",
        "package-philanthropy"
      ],
      "upsells": [
        "universe-professional",
        "distribution-events-api",
        "distribution-alerts-api",
        "distribution-relationships-api",
        "package-exec-insights",
        "package-equity-ma",
        "package-wealth",
        "f-relationships-1st",
        "f-relationships-2nd",
        "f-pathfinder",
        "f-client-networks",
        "f-news-alerts",
        "f-radar"
      ],
      "productDescription": "TBC",
      "sellable": false
    },
    "fs-fundraising-sf": {
      "cognitoGroups": [
        "universe-wealth",
        "distribution-altrata-web",
        "distribution-app-salesforce",
        "package-core",
        "package-philanthropy"
      ],
      "upsells": [
        "universe-professional",
        "package-exec-insights",
        "package-equity-ma",
        "package-wealth",
        "f-news-alerts"
      ],
      "productDescription": "TBC",
      "sellable": false
    },
    "fs-talent-basic": {
      "cognitoGroups": [
        "universe-professional",
        "distribution-altrata-web",
        "package-core",
        "package-exec-insights"
      ],
      "upsells": [
        "universe-wealth",
        "package-equity-ma",
        "package-wealth",
        "package-philanthropy",
        "f-news-alerts",
        "f-radar"
      ],
      "productDescription": "TBC",
      "sellable": false
    },
    "fs-talent-advanced": {
      "cognitoGroups": [
        "universe-professional",
        "distribution-altrata-web",
        "package-core",
        "package-exec-insights"
      ],
      "upsells": [
        "universe-wealth",
        "package-equity-ma",
        "package-wealth",
        "package-philanthropy",
        "f-news-alerts",
        "f-radar"
      ],
      "productDescription": "TBC",
      "sellable": false
    },
    "fs-talent-daas": {
      "cognitoGroups": [
        "universe-professional",
        "distribution-datafeed-sftp",
        "distribution-datafeed-s3",
        "distribution-datafeed-snowflake",
        "distribution-matching-api",
        "distribution-matching-sftp",
        "distribution-profile-api",
        "distribution-upds-api",
        "package-core",
        "package-exec-insights"
      ],
      "upsells": [
        "universe-wealth",
        "distribution-events-api",
        "distribution-alerts-api",
        "distribution-relationships-api",
        "package-equity-ma",
        "package-wealth",
        "package-philanthropy",
        "f-relationships-1st",
        "f-relationships-2nd",
        "f-pathfinder",
        "f-client-networks",
        "f-news-alerts",
        "f-radar"
      ],
      "productDescription": "TBC",
      "sellable": false
    },
    "fs-talent-sf": {
      "cognitoGroups": [
        "universe-professional",
        "distribution-altrata-web",
        "distribution-app-salesforce",
        "package-core",
        "package-exec-insights"
      ],
      "upsells": [
        "universe-wealth",
        "package-equity-ma",
        "package-wealth",
        "package-philanthropy",
        "f-pathfinder",
        "f-client-networks",
        "f-news-alerts"
      ],
      "productDescription": "TBC",
      "sellable": false
    }
  },
  "featureSetInclusions": {
    "fs-web-rrg": [
      "f-search",
      "f-list-management",
      "f-saml",
      "f-upsells",
      "f-contact-matching",
      "f-camp",
      "f-relationships-1st",
      "f-relationships-2nd",
      "f-pathfinder",
      "f-client-networks",
      "f-profile-downloads",
      "f-advanced-search",
      "f-modelling",
      "f-news-alerts",
      "f-radar"
    ],
    "fs-daas-rrg": [
      "f-search",
      "f-list-management",
      "f-saml",
      "f-upsells",
      "f-contact-matching",
      "f-camp",
      "f-pathfinder",
      "f-client-networks",
      "f-profile-downloads",
      "f-advanced-search",
      "f-modelling",
      "f-news-alerts",
      "f-radar"
    ],
    "fs-salesforce-rrg": [
      "f-search",
      "f-list-management",
      "f-saml",
      "f-contact-matching",
      "f-relationships-1st",
      "f-relationships-2nd",
      "f-profile-downloads",
      "f-advanced-search",
      "f-news-alerts"
    ],
    "fs-client-acquisition-b2b-basic": [
      "f-search",
      "f-list-management",
      "f-saml",
      "f-upsells",
      "f-contact-matching",
      "f-camp",
      "f-relationships-1st",
      "f-client-networks",
      "f-profile-downloads",
      "f-advanced-search"
    ],
    "fs-client-acquisition-b2b-advanced": [
      "f-search",
      "f-list-management",
      "f-saml",
      "f-upsells",
      "f-contact-matching",
      "f-camp",
      "f-relationships-1st",
      "f-relationships-2nd",
      "f-pathfinder",
      "f-client-networks",
      "f-profile-downloads",
      "f-advanced-search",
      "f-modelling"
    ],
    "fs-client-acquisition-b2b-daas": [
      "f-search",
      "f-contact-matching",
      "f-advanced-search"
    ],
    "fs-client-acquisition-b2b-sf": [
      "f-search",
      "f-list-management",
      "f-saml",
      "f-contact-matching",
      "f-relationships-1st",
      "f-relationships-2nd",
      "f-profile-downloads",
      "f-advanced-search"
    ],
    "fs-client-acquisition-b2c-basic": [
      "f-search",
      "f-list-management",
      "f-saml",
      "f-upsells",
      "f-contact-matching",
      "f-camp",
      "f-profile-downloads",
      "f-advanced-search"
    ],
    "fs-client-acquisition-b2c-advanced": [
      "f-search",
      "f-list-management",
      "f-saml",
      "f-upsells",
      "f-contact-matching",
      "f-camp",
      "f-relationships-1st",
      "f-relationships-2nd",
      "f-pathfinder",
      "f-client-networks",
      "f-profile-downloads",
      "f-advanced-search",
      "f-modelling"
    ],
    "fs-client-acquisition-b2c-daas": [
      "f-search",
      "f-contact-matching",
      "f-advanced-search"
    ],
    "fs-client-acquisition-b2c-sf": [
      "f-search",
      "f-list-management",
      "f-saml",
      "f-contact-matching",
      "f-relationships-1st",
      "f-relationships-2nd",
      "f-profile-downloads",
      "f-advanced-search"
    ],
    "fs-dealmakingpe-basic": [
      "f-search",
      "f-list-management",
      "f-saml",
      "f-upsells",
      "f-contact-matching",
      "f-camp",
      "f-relationships-1st",
      "f-client-networks",
      "f-profile-downloads",
      "f-advanced-search"
    ],
    "fs-dealmakingpe-advanced": [
      "f-search",
      "f-list-management",
      "f-saml",
      "f-upsells",
      "f-contact-matching",
      "f-camp",
      "f-relationships-1st",
      "f-relationships-2nd",
      "f-pathfinder",
      "f-client-networks",
      "f-profile-downloads",
      "f-advanced-search",
      "f-modelling"
    ],
    "fs-dealmakingpe-daas": [
      "f-search",
      "f-contact-matching",
      "f-advanced-search"
    ],
    "fs-dealmakingpe-sf": [
      "f-search",
      "f-list-management",
      "f-saml",
      "f-contact-matching",
      "f-relationships-1st",
      "f-relationships-2nd",
      "f-profile-downloads",
      "f-advanced-search"
    ],
    "fs-fundraising-basic": [
      "f-search",
      "f-list-management",
      "f-saml",
      "f-upsells",
      "f-contact-matching",
      "f-camp",
      "f-relationships-1st",
      "f-client-networks",
      "f-profile-downloads"
    ],
    "fs-fundraising-advanced": [
      "f-search",
      "f-list-management",
      "f-saml",
      "f-upsells",
      "f-contact-matching",
      "f-camp",
      "f-relationships-1st",
      "f-relationships-2nd",
      "f-pathfinder",
      "f-client-networks",
      "f-profile-downloads",
      "f-advanced-search",
      "f-modelling"
    ],
    "fs-fundraising-daas": [
      "f-search",
      "f-contact-matching",
      "f-advanced-search"
    ],
    "fs-fundraising-sf": [
      "f-search",
      "f-list-management",
      "f-saml",
      "f-contact-matching",
      "f-relationships-1st",
      "f-relationships-2nd",
      "f-profile-downloads",
      "f-advanced-search"
    ],
    "fs-talent-basic": [
      "f-search",
      "f-list-management",
      "f-saml",
      "f-upsells",
      "f-contact-matching",
      "f-camp",
      "f-relationships-1st",
      "f-client-networks",
      "f-profile-downloads"
    ],
    "fs-talent-advanced": [
      "f-search",
      "f-list-management",
      "f-saml",
      "f-upsells",
      "f-contact-matching",
      "f-camp",
      "f-relationships-1st",
      "f-relationships-2nd",
      "f-pathfinder",
      "f-client-networks",
      "f-profile-downloads",
      "f-advanced-search",
      "f-modelling"
    ],
    "fs-talent-daas": [
      "f-search",
      "f-contact-matching",
      "f-advanced-search"
    ],
    "fs-talent-sf": [
      "f-search",
      "f-list-management",
      "f-saml",
      "f-contact-matching",
      "f-relationships-1st",
      "f-relationships-2nd",
      "f-profile-downloads",
      "f-advanced-search"
    ]
  },
  "gridStatus": [
    {
      "id": "metadata-sellable",
      "enumeration-name": "Metadata",
      "type": "Metadata",
      "module": "Available for Sale",
      "fs-web-rrg": true,
      "fs-daas-rrg": true,
      "fs-salesforce-rrg": true,
      "fs-client-acquisition-b2b-basic": true,
      "fs-client-acquisition-b2b-advanced": true,
      "fs-client-acquisition-b2b-daas": true,
      "fs-client-acquisition-b2b-sf": true,
      "fs-client-acquisition-b2c-basic": true,
      "fs-client-acquisition-b2c-advanced": true,
      "fs-client-acquisition-b2c-daas": true,
      "fs-client-acquisition-b2c-sf": true,
      "fs-dealmakingpe-basic": true,
      "fs-dealmakingpe-advanced": true,
      "fs-dealmakingpe-daas": true,
      "fs-dealmakingpe-sf": true,
      "fs-fundraising-basic": true,
      "fs-fundraising-advanced": true,
      "fs-fundraising-daas": true,
      "fs-fundraising-sf": true,
      "fs-talent-basic": true,
      "fs-talent-advanced": true,
      "fs-talent-daas": true,
      "fs-talent-sf": true
    },
    {
      "id": "metadata-user-type",
      "enumeration-name": "UserType",
      "type": "Metadata",
      "module": "User Type",
      "fs-web-rrg": "HUMAN",
      "fs-daas-rrg": "SERVICE",
      "fs-salesforce-rrg": "ALL",
      "fs-client-acquisition-b2b-basic": "HUMAN",
      "fs-client-acquisition-b2b-advanced": "HUMAN",
      "fs-client-acquisition-b2b-daas": "SERVICE",
      "fs-client-acquisition-b2b-sf": "ALL",
      "fs-client-acquisition-b2c-basic": "HUMAN",
      "fs-client-acquisition-b2c-advanced": "HUMAN",
      "fs-client-acquisition-b2c-daas": "SERVICE",
      "fs-client-acquisition-b2c-sf": "ALL",
      "fs-dealmakingpe-basic": "HUMAN",
      "fs-dealmakingpe-advanced": "HUMAN",
      "fs-dealmakingpe-daas": "SERVICE",
      "fs-dealmakingpe-sf": "ALL",
      "fs-fundraising-basic": "HUMAN",
      "fs-fundraising-advanced": "HUMAN",
      "fs-fundraising-daas": "SERVICE",
      "fs-fundraising-sf": "ALL",
      "fs-talent-basic": "HUMAN",
      "fs-talent-advanced": "HUMAN",
      "fs-talent-daas": "SERVICE",
      "fs-talent-sf": "ALL"
    },
    {
      "id": "metadata-product-description",
      "enumeration-name": "ProductDescription",
      "type": "Metadata",
      "module": "Product Description",
      "fs-web-rrg": "Lorem ipsum dolor sit amet, consectetur adipiscing elit. Maecenas ut venenatis eros. Etiam purus nisl, fringilla et gravida nec, molestie a mi. Aenean laoreet semper neque, in finibus lacus viverra in. Curabitur venenatis lacus velit, quis rutrum enim elementum bibendum. Vivamus hendrerit elementum pulvinar. Etiam ultrices auctor felis id suscipit. Duis tristique felis non nulla pulvinar sodales. Pellentesque non pharetra metus, et faucibus nunc. Sed semper sapien at lacus posuere facilisis. Mauris volutpat dui non justo pretium, ac sagittis ligula mattis. Vestibulum ullamcorper, ipsum nec gravida placerat, massa nisl feugiat massa, ut rhoncus enim arcu nec augue. Cras sed tellus et est finibus laoreet. Aliquam ullamcorper sapien eget aliquet tincidunt. Nunc et elementum velit. Nunc mattis viverra ornare. Mauris malesuada, risus a pulvinar finibus, erat neque semper neque, sit amet porta mi magna a odio.",
      "fs-daas-rrg": "TBC",
      "fs-salesforce-rrg": "TBC",
      "fs-client-acquisition-b2b-basic": "TBC",
      "fs-client-acquisition-b2b-advanced": "TBC",
      "fs-client-acquisition-b2b-daas": "TBC",
      "fs-client-acquisition-b2b-sf": "TBC",
      "fs-client-acquisition-b2c-basic": "TBC",
      "fs-client-acquisition-b2c-advanced": "TBC",
      "fs-client-acquisition-b2c-daas": "TBC",
      "fs-client-acquisition-b2c-sf": "TBC",
      "fs-dealmakingpe-basic": "TBC",
      "fs-dealmakingpe-advanced": "TBC",
      "fs-dealmakingpe-daas": "TBC",
      "fs-dealmakingpe-sf": "TBC",
      "fs-fundraising-basic": "TBC",
      "fs-fundraising-advanced": "TBC",
      "fs-fundraising-daas": "TBC",
      "fs-fundraising-sf": "TBC",
      "fs-talent-basic": "TBC",
      "fs-talent-advanced": "TBC",
      "fs-talent-daas": "TBC",
      "fs-talent-sf": "TBC"
    },
    {
      "id": "universe-professional",
      "enumeration-name": "Professional",
      "type": "Universe",
      "module": "Executive & Company Universe",
      "fs-web-rrg": "included",
      "fs-daas-rrg": "included",
      "fs-client-acquisition-b2b-basic": "included",
      "fs-client-acquisition-b2b-advanced": "included",
      "fs-client-acquisition-b2b-daas": "included",
      "fs-client-acquisition-b2c-basic": "upsell",
      "fs-client-acquisition-b2c-advanced": "upsell",
      "fs-client-acquisition-b2c-daas": "upsell",
      "fs-dealmakingpe-basic": "included",
      "fs-dealmakingpe-advanced": "included",
      "fs-dealmakingpe-daas": "included",
      "fs-fundraising-basic": "upsell",
      "fs-fundraising-advanced": "upsell",
      "fs-fundraising-daas": "upsell",
      "fs-talent-basic": "included",
      "fs-talent-advanced": "included",
      "fs-talent-daas": "included",
      "fs-salesforce-rrg": "included",
      "fs-client-acquisition-b2b-sf": "included",
      "fs-client-acquisition-b2c-sf": "upsell",
      "fs-dealmakingpe-sf": "included",
      "fs-fundraising-sf": "upsell",
      "fs-talent-sf": "included"
    },
    {
      "id": "universe-wealth",
      "enumeration-name": "Wealth",
      "type": "Universe",
      "module": "Wealth Individual Universe",
      "fs-web-rrg": "included",
      "fs-daas-rrg": "included",
      "fs-client-acquisition-b2b-basic": "excluded",
      "fs-client-acquisition-b2b-advanced": "upsell",
      "fs-client-acquisition-b2b-daas": "upsell",
      "fs-client-acquisition-b2c-basic": "included",
      "fs-client-acquisition-b2c-advanced": "included",
      "fs-client-acquisition-b2c-daas": "included",
      "fs-dealmakingpe-basic": "upsell",
      "fs-dealmakingpe-advanced": "upsell",
      "fs-dealmakingpe-daas": "upsell",
      "fs-fundraising-basic": "included",
      "fs-fundraising-advanced": "included",
      "fs-fundraising-daas": "included",
      "fs-talent-basic": "upsell",
      "fs-talent-advanced": "upsell",
      "fs-talent-daas": "upsell",
      "fs-salesforce-rrg": "included",
      "fs-client-acquisition-b2b-sf": "upsell",
      "fs-client-acquisition-b2c-sf": "included",
      "fs-dealmakingpe-sf": "upsell",
      "fs-fundraising-sf": "included",
      "fs-talent-sf": "upsell"
    },
    {
      "id": "distribution-altrata-web",
      "enumeration-name": "AltrataWeb",
      "type": "Distribution",
      "module": "Altrata Website",
      "fs-web-rrg": "included",
      "fs-daas-rrg": "excluded",
      "fs-client-acquisition-b2b-basic": "included",
      "fs-client-acquisition-b2b-advanced": "included",
      "fs-client-acquisition-b2b-daas": "excluded",
      "fs-client-acquisition-b2c-basic": "included",
      "fs-client-acquisition-b2c-advanced": "included",
      "fs-client-acquisition-b2c-daas": "excluded",
      "fs-dealmakingpe-basic": "included",
      "fs-dealmakingpe-advanced": "included",
      "fs-dealmakingpe-daas": "excluded",
      "fs-fundraising-basic": "included",
      "fs-fundraising-advanced": "included",
      "fs-fundraising-daas": "excluded",
      "fs-talent-basic": "included",
      "fs-talent-advanced": "included",
      "fs-talent-daas": "excluded",
      "fs-salesforce-rrg": "excluded",
      "fs-client-acquisition-b2b-sf": "included",
      "fs-client-acquisition-b2c-sf": "included",
      "fs-dealmakingpe-sf": "included",
      "fs-fundraising-sf": "included",
      "fs-talent-sf": "included"
    },
    {
      "id": "distribution-datafeed-sftp",
      "enumeration-name": "DatafeedSFTP",
      "type": "Distribution",
      "module": "Datafeed via SFTP",
      "fs-web-rrg": "excluded",
      "fs-daas-rrg": "included",
      "fs-client-acquisition-b2b-basic": "excluded",
      "fs-client-acquisition-b2b-advanced": "excluded",
      "fs-client-acquisition-b2b-daas": "included",
      "fs-client-acquisition-b2c-basic": "excluded",
      "fs-client-acquisition-b2c-advanced": "excluded",
      "fs-client-acquisition-b2c-daas": "included",
      "fs-dealmakingpe-basic": "excluded",
      "fs-dealmakingpe-advanced": "excluded",
      "fs-dealmakingpe-daas": "included",
      "fs-fundraising-basic": "excluded",
      "fs-fundraising-advanced": "excluded",
      "fs-fundraising-daas": "included",
      "fs-talent-basic": "excluded",
      "fs-talent-advanced": "excluded",
      "fs-talent-daas": "included",
      "fs-salesforce-rrg": "excluded",
      "fs-client-acquisition-b2b-sf": "excluded",
      "fs-client-acquisition-b2c-sf": "excluded",
      "fs-dealmakingpe-sf": "excluded",
      "fs-fundraising-sf": "excluded",
      "fs-talent-sf": "excluded"
    },
    {
      "id": "distribution-datafeed-s3",
      "enumeration-name": "DatafeedS3",
      "type": "Distribution",
      "module": "Datafeed via S3",
      "fs-web-rrg": "excluded",
      "fs-daas-rrg": "included",
      "fs-client-acquisition-b2b-basic": "excluded",
      "fs-client-acquisition-b2b-advanced": "excluded",
      "fs-client-acquisition-b2b-daas": "included",
      "fs-client-acquisition-b2c-basic": "excluded",
      "fs-client-acquisition-b2c-advanced": "excluded",
      "fs-client-acquisition-b2c-daas": "included",
      "fs-dealmakingpe-basic": "excluded",
      "fs-dealmakingpe-advanced": "excluded",
      "fs-dealmakingpe-daas": "included",
      "fs-fundraising-basic": "excluded",
      "fs-fundraising-advanced": "excluded",
      "fs-fundraising-daas": "included",
      "fs-talent-basic": "excluded",
      "fs-talent-advanced": "excluded",
      "fs-talent-daas": "included",
      "fs-salesforce-rrg": "excluded",
      "fs-client-acquisition-b2b-sf": "excluded",
      "fs-client-acquisition-b2c-sf": "excluded",
      "fs-dealmakingpe-sf": "excluded",
      "fs-fundraising-sf": "excluded",
      "fs-talent-sf": "excluded"
    },
    {
      "id": "distribution-datafeed-snowflake",
      "enumeration-name": "DatafeedSnowflake",
      "type": "Distribution",
      "module": "Datafeed via Snowflake",
      "fs-web-rrg": "excluded",
      "fs-daas-rrg": "included",
      "fs-client-acquisition-b2b-basic": "excluded",
      "fs-client-acquisition-b2b-advanced": "excluded",
      "fs-client-acquisition-b2b-daas": "included",
      "fs-client-acquisition-b2c-basic": "excluded",
      "fs-client-acquisition-b2c-advanced": "excluded",
      "fs-client-acquisition-b2c-daas": "included",
      "fs-dealmakingpe-basic": "excluded",
      "fs-dealmakingpe-advanced": "excluded",
      "fs-dealmakingpe-daas": "included",
      "fs-fundraising-basic": "excluded",
      "fs-fundraising-advanced": "excluded",
      "fs-fundraising-daas": "included",
      "fs-talent-basic": "excluded",
      "fs-talent-advanced": "excluded",
      "fs-talent-daas": "included",
      "fs-salesforce-rrg": "excluded",
      "fs-client-acquisition-b2b-sf": "excluded",
      "fs-client-acquisition-b2c-sf": "excluded",
      "fs-dealmakingpe-sf": "excluded",
      "fs-fundraising-sf": "excluded",
      "fs-talent-sf": "excluded"
    },
    {
      "id": "distribution-app-salesforce",
      "enumeration-name": "Salesforce",
      "type": "Distribution",
      "module": "Salesforce",
      "fs-web-rrg": "excluded",
      "fs-daas-rrg": "excluded",
      "fs-client-acquisition-b2b-basic": "excluded",
      "fs-client-acquisition-b2b-advanced": "excluded",
      "fs-client-acquisition-b2b-daas": "excluded",
      "fs-client-acquisition-b2c-basic": "excluded",
      "fs-client-acquisition-b2c-advanced": "excluded",
      "fs-client-acquisition-b2c-daas": "excluded",
      "fs-dealmakingpe-basic": "excluded",
      "fs-dealmakingpe-advanced": "excluded",
      "fs-dealmakingpe-daas": "excluded",
      "fs-fundraising-basic": "excluded",
      "fs-fundraising-advanced": "excluded",
      "fs-fundraising-daas": "excluded",
      "fs-talent-basic": "excluded",
      "fs-talent-advanced": "excluded",
      "fs-talent-daas": "excluded",
      "fs-salesforce-rrg": "included",
      "fs-client-acquisition-b2b-sf": "included",
      "fs-client-acquisition-b2c-sf": "included",
      "fs-dealmakingpe-sf": "included",
      "fs-fundraising-sf": "included",
      "fs-talent-sf": "included"
    },
    {
      "id": "distribution-matching-api",
      "enumeration-name": "MatchingAPI",
      "type": "Distribution",
      "module": "Matching via API",
      "fs-web-rrg": "excluded",
      "fs-daas-rrg": "included",
      "fs-client-acquisition-b2b-basic": "excluded",
      "fs-client-acquisition-b2b-advanced": "excluded",
      "fs-client-acquisition-b2b-daas": "included",
      "fs-client-acquisition-b2c-basic": "excluded",
      "fs-client-acquisition-b2c-advanced": "excluded",
      "fs-client-acquisition-b2c-daas": "included",
      "fs-dealmakingpe-basic": "excluded",
      "fs-dealmakingpe-advanced": "excluded",
      "fs-dealmakingpe-daas": "included",
      "fs-fundraising-basic": "excluded",
      "fs-fundraising-advanced": "excluded",
      "fs-fundraising-daas": "included",
      "fs-talent-basic": "excluded",
      "fs-talent-advanced": "excluded",
      "fs-talent-daas": "included",
      "fs-salesforce-rrg": "excluded",
      "fs-client-acquisition-b2b-sf": "excluded",
      "fs-client-acquisition-b2c-sf": "excluded",
      "fs-dealmakingpe-sf": "excluded",
      "fs-fundraising-sf": "excluded",
      "fs-talent-sf": "excluded"
    },
    {
      "id": "distribution-matching-sftp",
      "enumeration-name": "MatchingSFTP",
      "type": "Distribution",
      "module": "Matching via SFTP",
      "fs-web-rrg": "excluded",
      "fs-daas-rrg": "included",
      "fs-client-acquisition-b2b-basic": "excluded",
      "fs-client-acquisition-b2b-advanced": "excluded",
      "fs-client-acquisition-b2b-daas": "included",
      "fs-client-acquisition-b2c-basic": "excluded",
      "fs-client-acquisition-b2c-advanced": "excluded",
      "fs-client-acquisition-b2c-daas": "included",
      "fs-dealmakingpe-basic": "excluded",
      "fs-dealmakingpe-advanced": "excluded",
      "fs-dealmakingpe-daas": "included",
      "fs-fundraising-basic": "excluded",
      "fs-fundraising-advanced": "excluded",
      "fs-fundraising-daas": "included",
      "fs-talent-basic": "excluded",
      "fs-talent-advanced": "excluded",
      "fs-talent-daas": "included",
      "fs-salesforce-rrg": "excluded",
      "fs-client-acquisition-b2b-sf": "excluded",
      "fs-client-acquisition-b2c-sf": "excluded",
      "fs-dealmakingpe-sf": "excluded",
      "fs-fundraising-sf": "excluded",
      "fs-talent-sf": "excluded"
    },
    {
      "id": "distribution-profile-api",
      "enumeration-name": "ProfileAPI",
      "type": "Distribution",
      "module": "Profile API",
      "fs-web-rrg": "excluded",
      "fs-daas-rrg": "included",
      "fs-client-acquisition-b2b-basic": "excluded",
      "fs-client-acquisition-b2b-advanced": "excluded",
      "fs-client-acquisition-b2b-daas": "included",
      "fs-client-acquisition-b2c-basic": "excluded",
      "fs-client-acquisition-b2c-advanced": "excluded",
      "fs-client-acquisition-b2c-daas": "included",
      "fs-dealmakingpe-basic": "excluded",
      "fs-dealmakingpe-advanced": "excluded",
      "fs-dealmakingpe-daas": "included",
      "fs-fundraising-basic": "excluded",
      "fs-fundraising-advanced": "excluded",
      "fs-fundraising-daas": "included",
      "fs-talent-basic": "excluded",
      "fs-talent-advanced": "excluded",
      "fs-talent-daas": "included",
      "fs-salesforce-rrg": "excluded",
      "fs-client-acquisition-b2b-sf": "excluded",
      "fs-client-acquisition-b2c-sf": "excluded",
      "fs-dealmakingpe-sf": "excluded",
      "fs-fundraising-sf": "excluded",
      "fs-talent-sf": "excluded"
    },
    {
      "id": "distribution-upds-api",
      "enumeration-name": "UPDSAPI",
      "type": "Distribution",
      "module": "UPDS API",
      "fs-web-rrg": "excluded",
      "fs-daas-rrg": "included",
      "fs-client-acquisition-b2b-basic": "excluded",
      "fs-client-acquisition-b2b-advanced": "excluded",
      "fs-client-acquisition-b2b-daas": "included",
      "fs-client-acquisition-b2c-basic": "excluded",
      "fs-client-acquisition-b2c-advanced": "excluded",
      "fs-client-acquisition-b2c-daas": "included",
      "fs-dealmakingpe-basic": "excluded",
      "fs-dealmakingpe-advanced": "excluded",
      "fs-dealmakingpe-daas": "included",
      "fs-fundraising-basic": "excluded",
      "fs-fundraising-advanced": "excluded",
      "fs-fundraising-daas": "included",
      "fs-talent-basic": "excluded",
      "fs-talent-advanced": "excluded",
      "fs-talent-daas": "included",
      "fs-salesforce-rrg": "excluded",
      "fs-client-acquisition-b2b-sf": "excluded",
      "fs-client-acquisition-b2c-sf": "excluded",
      "fs-dealmakingpe-sf": "excluded",
      "fs-fundraising-sf": "excluded",
      "fs-talent-sf": "excluded"
    },
    {
      "id": "distribution-events-api",
      "enumeration-name": "EventsAPI",
      "type": "Distribution",
      "module": "Events API",
      "fs-web-rrg": "excluded",
      "fs-daas-rrg": "included",
      "fs-client-acquisition-b2b-basic": "excluded",
      "fs-client-acquisition-b2b-advanced": "excluded",
      "fs-client-acquisition-b2b-daas": "upsell",
      "fs-client-acquisition-b2c-basic": "excluded",
      "fs-client-acquisition-b2c-advanced": "excluded",
      "fs-client-acquisition-b2c-daas": "upsell",
      "fs-dealmakingpe-basic": "excluded",
      "fs-dealmakingpe-advanced": "excluded",
      "fs-dealmakingpe-daas": "upsell",
      "fs-fundraising-basic": "excluded",
      "fs-fundraising-advanced": "excluded",
      "fs-fundraising-daas": "upsell",
      "fs-talent-basic": "excluded",
      "fs-talent-advanced": "excluded",
      "fs-talent-daas": "upsell",
      "fs-salesforce-rrg": "excluded",
      "fs-client-acquisition-b2b-sf": "excluded",
      "fs-client-acquisition-b2c-sf": "excluded",
      "fs-dealmakingpe-sf": "excluded",
      "fs-fundraising-sf": "excluded",
      "fs-talent-sf": "excluded"
    },
    {
      "id": "distribution-alerts-api",
      "enumeration-name": "AlertsAPI",
      "type": "Distribution",
      "module": "Alerts API",
      "fs-web-rrg": "excluded",
      "fs-daas-rrg": "included",
      "fs-client-acquisition-b2b-basic": "excluded",
      "fs-client-acquisition-b2b-advanced": "excluded",
      "fs-client-acquisition-b2b-daas": "upsell",
      "fs-client-acquisition-b2c-basic": "excluded",
      "fs-client-acquisition-b2c-advanced": "excluded",
      "fs-client-acquisition-b2c-daas": "upsell",
      "fs-dealmakingpe-basic": "excluded",
      "fs-dealmakingpe-advanced": "excluded",
      "fs-dealmakingpe-daas": "upsell",
      "fs-fundraising-basic": "excluded",
      "fs-fundraising-advanced": "excluded",
      "fs-fundraising-daas": "upsell",
      "fs-talent-basic": "excluded",
      "fs-talent-advanced": "excluded",
      "fs-talent-daas": "upsell",
      "fs-salesforce-rrg": "excluded",
      "fs-client-acquisition-b2b-sf": "excluded",
      "fs-client-acquisition-b2c-sf": "excluded",
      "fs-dealmakingpe-sf": "excluded",
      "fs-fundraising-sf": "excluded",
      "fs-talent-sf": "excluded"
    },
    {
      "id": "distribution-relationships-api",
      "enumeration-name": "RelationshipsAPI",
      "type": "Distribution",
      "module": "Relationships API",
      "fs-web-rrg": "excluded",
      "fs-daas-rrg": "excluded",
      "fs-client-acquisition-b2b-basic": "excluded",
      "fs-client-acquisition-b2b-advanced": "excluded",
      "fs-client-acquisition-b2b-daas": "upsell",
      "fs-client-acquisition-b2c-basic": "excluded",
      "fs-client-acquisition-b2c-advanced": "excluded",
      "fs-client-acquisition-b2c-daas": "upsell",
      "fs-dealmakingpe-basic": "excluded",
      "fs-dealmakingpe-advanced": "excluded",
      "fs-dealmakingpe-daas": "upsell",
      "fs-fundraising-basic": "excluded",
      "fs-fundraising-advanced": "excluded",
      "fs-fundraising-daas": "upsell",
      "fs-talent-basic": "excluded",
      "fs-talent-advanced": "excluded",
      "fs-talent-daas": "upsell",
      "fs-salesforce-rrg": "excluded",
      "fs-client-acquisition-b2b-sf": "excluded",
      "fs-client-acquisition-b2c-sf": "excluded",
      "fs-dealmakingpe-sf": "excluded",
      "fs-fundraising-sf": "excluded",
      "fs-talent-sf": "excluded"
    },
    {
      "id": "package-core",
      "enumeration-name": "Core",
      "type": "Package",
      "module": "Core Data Types",
      "fs-web-rrg": "included",
      "fs-daas-rrg": "included",
      "fs-client-acquisition-b2b-basic": "included",
      "fs-client-acquisition-b2b-advanced": "included",
      "fs-client-acquisition-b2b-daas": "included",
      "fs-client-acquisition-b2c-basic": "included",
      "fs-client-acquisition-b2c-advanced": "included",
      "fs-client-acquisition-b2c-daas": "included",
      "fs-dealmakingpe-basic": "included",
      "fs-dealmakingpe-advanced": "included",
      "fs-dealmakingpe-daas": "included",
      "fs-fundraising-basic": "included",
      "fs-fundraising-advanced": "included",
      "fs-fundraising-daas": "included",
      "fs-talent-basic": "included",
      "fs-talent-advanced": "included",
      "fs-talent-daas": "included",
      "fs-salesforce-rrg": "included",
      "fs-client-acquisition-b2b-sf": "included",
      "fs-client-acquisition-b2c-sf": "included",
      "fs-dealmakingpe-sf": "included",
      "fs-fundraising-sf": "included",
      "fs-talent-sf": "included"
    },
    {
      "id": "package-exec-insights",
      "enumeration-name": "ExecutiveInsights",
      "type": "Package",
      "module": "Executive Insights",
      "fs-web-rrg": "included",
      "fs-daas-rrg": "included",
      "fs-client-acquisition-b2b-basic": "included",
      "fs-client-acquisition-b2b-advanced": "included",
      "fs-client-acquisition-b2b-daas": "included",
      "fs-client-acquisition-b2c-basic": "upsell",
      "fs-client-acquisition-b2c-advanced": "upsell",
      "fs-client-acquisition-b2c-daas": "upsell",
      "fs-dealmakingpe-basic": "included",
      "fs-dealmakingpe-advanced": "included",
      "fs-dealmakingpe-daas": "included",
      "fs-fundraising-basic": "upsell",
      "fs-fundraising-advanced": "upsell",
      "fs-fundraising-daas": "upsell",
      "fs-talent-basic": "included",
      "fs-talent-advanced": "included",
      "fs-talent-daas": "included",
      "fs-salesforce-rrg": "included",
      "fs-client-acquisition-b2b-sf": "included",
      "fs-client-acquisition-b2c-sf": "included",
      "fs-dealmakingpe-sf": "included",
      "fs-fundraising-sf": "upsell",
      "fs-talent-sf": "included"
    },
    {
      "id": "package-equity-ma",
      "enumeration-name": "PrivateEquityMnA",
      "type": "Package",
      "module": "Private Equity & M&A",
      "fs-web-rrg": "included",
      "fs-daas-rrg": "included",
      "fs-client-acquisition-b2b-basic": "upsell",
      "fs-client-acquisition-b2b-advanced": "upsell",
      "fs-client-acquisition-b2b-daas": "upsell",
      "fs-client-acquisition-b2c-basic": "upsell",
      "fs-client-acquisition-b2c-advanced": "upsell",
      "fs-client-acquisition-b2c-daas": "upsell",
      "fs-dealmakingpe-basic": "upsell",
      "fs-dealmakingpe-advanced": "upsell",
      "fs-dealmakingpe-daas": "upsell",
      "fs-fundraising-basic": "upsell",
      "fs-fundraising-advanced": "upsell",
      "fs-fundraising-daas": "upsell",
      "fs-talent-basic": "upsell",
      "fs-talent-advanced": "upsell",
      "fs-talent-daas": "upsell",
      "fs-salesforce-rrg": "included",
      "fs-client-acquisition-b2b-sf": "upsell",
      "fs-client-acquisition-b2c-sf": "upsell",
      "fs-dealmakingpe-sf": "upsell",
      "fs-fundraising-sf": "upsell",
      "fs-talent-sf": "upsell"
    },
    {
      "id": "package-wealth",
      "enumeration-name": "Wealth",
      "type": "Package",
      "module": "Wealth Insight",
      "fs-web-rrg": "included",
      "fs-daas-rrg": "included",
      "fs-client-acquisition-b2b-basic": "upsell",
      "fs-client-acquisition-b2b-advanced": "upsell",
      "fs-client-acquisition-b2b-daas": "upsell",
      "fs-client-acquisition-b2c-basic": "included",
      "fs-client-acquisition-b2c-advanced": "included",
      "fs-client-acquisition-b2c-daas": "included",
      "fs-dealmakingpe-basic": "upsell",
      "fs-dealmakingpe-advanced": "upsell",
      "fs-dealmakingpe-daas": "upsell",
      "fs-fundraising-basic": "upsell",
      "fs-fundraising-advanced": "upsell",
      "fs-fundraising-daas": "upsell",
      "fs-talent-basic": "upsell",
      "fs-talent-advanced": "upsell",
      "fs-talent-daas": "upsell",
      "fs-salesforce-rrg": "included",
      "fs-client-acquisition-b2b-sf": "upsell",
      "fs-client-acquisition-b2c-sf": "included",
      "fs-dealmakingpe-sf": "upsell",
      "fs-fundraising-sf": "upsell",
      "fs-talent-sf": "upsell"
    },
    {
      "id": "package-philanthropy",
      "enumeration-name": "Philanthropy",
      "type": "Package",
      "module": "Philanthropy & Political Donations",
      "fs-web-rrg": "included",
      "fs-daas-rrg": "included",
      "fs-client-acquisition-b2b-basic": "upsell",
      "fs-client-acquisition-b2b-advanced": "upsell",
      "fs-client-acquisition-b2b-daas": "upsell",
      "fs-client-acquisition-b2c-basic": "upsell",
      "fs-client-acquisition-b2c-advanced": "upsell",
      "fs-client-acquisition-b2c-daas": "upsell",
      "fs-dealmakingpe-basic": "upsell",
      "fs-dealmakingpe-advanced": "upsell",
      "fs-dealmakingpe-daas": "upsell",
      "fs-fundraising-basic": "included",
      "fs-fundraising-advanced": "included",
      "fs-fundraising-daas": "included",
      "fs-talent-basic": "upsell",
      "fs-talent-advanced": "upsell",
      "fs-talent-daas": "upsell",
      "fs-salesforce-rrg": "included",
      "fs-client-acquisition-b2b-sf": "upsell",
      "fs-client-acquisition-b2c-sf": "upsell",
      "fs-dealmakingpe-sf": "upsell",
      "fs-fundraising-sf": "included",
      "fs-talent-sf": "upsell"
    },
    {
      "id": "f-search",
      "enumeration-name": "Search",
      "type": "Feature",
      "module": "Basic Search",
      "fs-web-rrg": "included",
      "fs-daas-rrg": "included",
      "fs-client-acquisition-b2b-basic": "included",
      "fs-client-acquisition-b2b-advanced": "included",
      "fs-client-acquisition-b2b-daas": "included",
      "fs-client-acquisition-b2c-basic": "included",
      "fs-client-acquisition-b2c-advanced": "included",
      "fs-client-acquisition-b2c-daas": "included",
      "fs-dealmakingpe-basic": "included",
      "fs-dealmakingpe-advanced": "included",
      "fs-dealmakingpe-daas": "included",
      "fs-fundraising-basic": "included",
      "fs-fundraising-advanced": "included",
      "fs-fundraising-daas": "included",
      "fs-talent-basic": "included",
      "fs-talent-advanced": "included",
      "fs-talent-daas": "included",
      "fs-salesforce-rrg": "included",
      "fs-client-acquisition-b2b-sf": "included",
      "fs-client-acquisition-b2c-sf": "included",
      "fs-dealmakingpe-sf": "included",
      "fs-fundraising-sf": "included",
      "fs-talent-sf": "included"
    },
    {
      "id": "f-list-management",
      "enumeration-name": "ListManagement",
      "type": "Feature",
      "module": "List Management",
      "fs-web-rrg": "included",
      "fs-daas-rrg": "included",
      "fs-client-acquisition-b2b-basic": "included",
      "fs-client-acquisition-b2b-advanced": "included",
      "fs-client-acquisition-b2b-daas": "excluded",
      "fs-client-acquisition-b2c-basic": "included",
      "fs-client-acquisition-b2c-advanced": "included",
      "fs-client-acquisition-b2c-daas": "excluded",
      "fs-dealmakingpe-basic": "included",
      "fs-dealmakingpe-advanced": "included",
      "fs-dealmakingpe-daas": "excluded",
      "fs-fundraising-basic": "included",
      "fs-fundraising-advanced": "included",
      "fs-fundraising-daas": "excluded",
      "fs-talent-basic": "included",
      "fs-talent-advanced": "included",
      "fs-talent-daas": "excluded",
      "fs-salesforce-rrg": "included",
      "fs-client-acquisition-b2b-sf": "included",
      "fs-client-acquisition-b2c-sf": "included",
      "fs-dealmakingpe-sf": "included",
      "fs-fundraising-sf": "included",
      "fs-talent-sf": "included"
    },
    {
      "id": "f-saml",
      "enumeration-name": "SAML",
      "type": "Feature",
      "module": "SAML (SSO)",
      "fs-web-rrg": "included",
      "fs-daas-rrg": "included",
      "fs-client-acquisition-b2b-basic": "included",
      "fs-client-acquisition-b2b-advanced": "included",
      "fs-client-acquisition-b2b-daas": "excluded",
      "fs-client-acquisition-b2c-basic": "included",
      "fs-client-acquisition-b2c-advanced": "included",
      "fs-client-acquisition-b2c-daas": "excluded",
      "fs-dealmakingpe-basic": "included",
      "fs-dealmakingpe-advanced": "included",
      "fs-dealmakingpe-daas": "excluded",
      "fs-fundraising-basic": "included",
      "fs-fundraising-advanced": "included",
      "fs-fundraising-daas": "excluded",
      "fs-talent-basic": "included",
      "fs-talent-advanced": "included",
      "fs-talent-daas": "excluded",
      "fs-salesforce-rrg": "included",
      "fs-client-acquisition-b2b-sf": "included",
      "fs-client-acquisition-b2c-sf": "included",
      "fs-dealmakingpe-sf": "included",
      "fs-fundraising-sf": "included",
      "fs-talent-sf": "included"
    },
    {
      "id": "f-upsells",
      "enumeration-name": "Upsells",
      "type": "Feature",
      "module": "In-Product Upsells",
      "fs-web-rrg": "included",
      "fs-daas-rrg": "included",
      "fs-client-acquisition-b2b-basic": "included",
      "fs-client-acquisition-b2b-advanced": "included",
      "fs-client-acquisition-b2b-daas": "excluded",
      "fs-client-acquisition-b2c-basic": "included",
      "fs-client-acquisition-b2c-advanced": "included",
      "fs-client-acquisition-b2c-daas": "excluded",
      "fs-dealmakingpe-basic": "included",
      "fs-dealmakingpe-advanced": "included",
      "fs-dealmakingpe-daas": "excluded",
      "fs-fundraising-basic": "included",
      "fs-fundraising-advanced": "included",
      "fs-fundraising-daas": "excluded",
      "fs-talent-basic": "included",
      "fs-talent-advanced": "included",
      "fs-talent-daas": "excluded",
      "fs-salesforce-rrg": "excluded",
      "fs-client-acquisition-b2b-sf": "excluded",
      "fs-client-acquisition-b2c-sf": "excluded",
      "fs-dealmakingpe-sf": "excluded",
      "fs-fundraising-sf": "excluded",
      "fs-talent-sf": "excluded"
    },
    {
      "id": "f-contact-matching",
      "enumeration-name": "ContactMatching",
      "type": "Feature",
      "module": "Web Contact Upload & Matching",
      "fs-web-rrg": "included",
      "fs-daas-rrg": "included",
      "fs-client-acquisition-b2b-basic": "included",
      "fs-client-acquisition-b2b-advanced": "included",
      "fs-client-acquisition-b2b-daas": "included",
      "fs-client-acquisition-b2c-basic": "included",
      "fs-client-acquisition-b2c-advanced": "included",
      "fs-client-acquisition-b2c-daas": "included",
      "fs-dealmakingpe-basic": "included",
      "fs-dealmakingpe-advanced": "included",
      "fs-dealmakingpe-daas": "included",
      "fs-fundraising-basic": "included",
      "fs-fundraising-advanced": "included",
      "fs-fundraising-daas": "included",
      "fs-talent-basic": "included",
      "fs-talent-advanced": "included",
      "fs-talent-daas": "included",
      "fs-salesforce-rrg": "included",
      "fs-client-acquisition-b2b-sf": "included",
      "fs-client-acquisition-b2c-sf": "included",
      "fs-dealmakingpe-sf": "included",
      "fs-fundraising-sf": "included",
      "fs-talent-sf": "included"
    },
    {
      "id": "f-camp",
      "enumeration-name": "CAMP",
      "type": "Feature",
      "module": "Client Access Management Portal (CAMP)",
      "fs-web-rrg": "included",
      "fs-daas-rrg": "included",
      "fs-client-acquisition-b2b-basic": "included",
      "fs-client-acquisition-b2b-advanced": "included",
      "fs-client-acquisition-b2b-daas": "excluded",
      "fs-client-acquisition-b2c-basic": "included",
      "fs-client-acquisition-b2c-advanced": "included",
      "fs-client-acquisition-b2c-daas": "excluded",
      "fs-dealmakingpe-basic": "included",
      "fs-dealmakingpe-advanced": "included",
      "fs-dealmakingpe-daas": "excluded",
      "fs-fundraising-basic": "included",
      "fs-fundraising-advanced": "included",
      "fs-fundraising-daas": "excluded",
      "fs-talent-basic": "included",
      "fs-talent-advanced": "included",
      "fs-talent-daas": "excluded",
      "fs-salesforce-rrg": "excluded",
      "fs-client-acquisition-b2b-sf": "excluded",
      "fs-client-acquisition-b2c-sf": "excluded",
      "fs-dealmakingpe-sf": "excluded",
      "fs-fundraising-sf": "excluded",
      "fs-talent-sf": "excluded"
    },
    {
      "id": "f-relationships-1st",
      "enumeration-name": "Relationships1stDegree",
      "type": "Feature",
      "module": "1st Degree Relationships",
      "fs-web-rrg": "included",
      "fs-daas-rrg": "excluded",
      "fs-client-acquisition-b2b-basic": "included",
      "fs-client-acquisition-b2b-advanced": "included",
      "fs-client-acquisition-b2b-daas": "upsell",
      "fs-client-acquisition-b2c-basic": "excluded",
      "fs-client-acquisition-b2c-advanced": "included",
      "fs-client-acquisition-b2c-daas": "upsell",
      "fs-dealmakingpe-basic": "included",
      "fs-dealmakingpe-advanced": "included",
      "fs-dealmakingpe-daas": "upsell",
      "fs-fundraising-basic": "included",
      "fs-fundraising-advanced": "included",
      "fs-fundraising-daas": "upsell",
      "fs-talent-basic": "included",
      "fs-talent-advanced": "included",
      "fs-talent-daas": "upsell",
      "fs-salesforce-rrg": "included",
      "fs-client-acquisition-b2b-sf": "included",
      "fs-client-acquisition-b2c-sf": "included",
      "fs-dealmakingpe-sf": "included",
      "fs-fundraising-sf": "included",
      "fs-talent-sf": "included"
    },
    {
      "id": "f-relationships-2nd",
      "enumeration-name": "Relationships2ndDegree",
      "type": "Feature",
      "module": "2nd Degree Relationships",
      "fs-web-rrg": "included",
      "fs-daas-rrg": "excluded",
      "fs-client-acquisition-b2b-basic": "excluded",
      "fs-client-acquisition-b2b-advanced": "included",
      "fs-client-acquisition-b2b-daas": "upsell",
      "fs-client-acquisition-b2c-basic": "excluded",
      "fs-client-acquisition-b2c-advanced": "included",
      "fs-client-acquisition-b2c-daas": "upsell",
      "fs-dealmakingpe-basic": "excluded",
      "fs-dealmakingpe-advanced": "included",
      "fs-dealmakingpe-daas": "upsell",
      "fs-fundraising-basic": "excluded",
      "fs-fundraising-advanced": "included",
      "fs-fundraising-daas": "upsell",
      "fs-talent-basic": "excluded",
      "fs-talent-advanced": "included",
      "fs-talent-daas": "upsell",
      "fs-salesforce-rrg": "included",
      "fs-client-acquisition-b2b-sf": "included",
      "fs-client-acquisition-b2c-sf": "included",
      "fs-dealmakingpe-sf": "included",
      "fs-fundraising-sf": "included",
      "fs-talent-sf": "included"
    },
    {
      "id": "f-pathfinder",
      "enumeration-name": "Pathfinder",
      "type": "Feature",
      "module": "Pathfinder",
      "fs-web-rrg": "included",
      "fs-daas-rrg": "included",
      "fs-client-acquisition-b2b-basic": "excluded",
      "fs-client-acquisition-b2b-advanced": "included",
      "fs-client-acquisition-b2b-daas": "upsell",
      "fs-client-acquisition-b2c-basic": "excluded",
      "fs-client-acquisition-b2c-advanced": "included",
      "fs-client-acquisition-b2c-daas": "upsell",
      "fs-dealmakingpe-basic": "excluded",
      "fs-dealmakingpe-advanced": "included",
      "fs-dealmakingpe-daas": "upsell",
      "fs-fundraising-basic": "excluded",
      "fs-fundraising-advanced": "included",
      "fs-fundraising-daas": "upsell",
      "fs-talent-basic": "excluded",
      "fs-talent-advanced": "included",
      "fs-talent-daas": "upsell",
      "fs-salesforce-rrg": "excluded",
      "fs-client-acquisition-b2b-sf": "excluded",
      "fs-client-acquisition-b2c-sf": "excluded",
      "fs-dealmakingpe-sf": "excluded",
      "fs-fundraising-sf": "excluded",
      "fs-talent-sf": "upsell"
    },
    {
      "id": "f-client-networks",
      "enumeration-name": "ClientNetworks",
      "type": "Feature",
      "module": "Foundation / Client Networks",
      "fs-web-rrg": "included",
      "fs-daas-rrg": "included",
      "fs-client-acquisition-b2b-basic": "included",
      "fs-client-acquisition-b2b-advanced": "included",
      "fs-client-acquisition-b2b-daas": "upsell",
      "fs-client-acquisition-b2c-basic": "excluded",
      "fs-client-acquisition-b2c-advanced": "included",
      "fs-client-acquisition-b2c-daas": "upsell",
      "fs-dealmakingpe-basic": "included",
      "fs-dealmakingpe-advanced": "included",
      "fs-dealmakingpe-daas": "upsell",
      "fs-fundraising-basic": "included",
      "fs-fundraising-advanced": "included",
      "fs-fundraising-daas": "upsell",
      "fs-talent-basic": "included",
      "fs-talent-advanced": "included",
      "fs-talent-daas": "upsell",
      "fs-salesforce-rrg": "excluded",
      "fs-client-acquisition-b2b-sf": "excluded",
      "fs-client-acquisition-b2c-sf": "excluded",
      "fs-dealmakingpe-sf": "excluded",
      "fs-fundraising-sf": "excluded",
      "fs-talent-sf": "upsell"
    },
    {
      "id": "f-profile-downloads",
      "enumeration-name": "ProfileDownloads",
      "type": "Feature",
      "module": "Profile Downloads",
      "fs-web-rrg": "included",
      "fs-daas-rrg": "included",
      "fs-client-acquisition-b2b-basic": "included",
      "fs-client-acquisition-b2b-advanced": "included",
      "fs-client-acquisition-b2b-daas": "excluded",
      "fs-client-acquisition-b2c-basic": "included",
      "fs-client-acquisition-b2c-advanced": "included",
      "fs-client-acquisition-b2c-daas": "excluded",
      "fs-dealmakingpe-basic": "included",
      "fs-dealmakingpe-advanced": "included",
      "fs-dealmakingpe-daas": "excluded",
      "fs-fundraising-basic": "included",
      "fs-fundraising-advanced": "included",
      "fs-fundraising-daas": "excluded",
      "fs-talent-basic": "included",
      "fs-talent-advanced": "included",
      "fs-talent-daas": "excluded",
      "fs-salesforce-rrg": "included",
      "fs-client-acquisition-b2b-sf": "included",
      "fs-client-acquisition-b2c-sf": "included",
      "fs-dealmakingpe-sf": "included",
      "fs-fundraising-sf": "included",
      "fs-talent-sf": "included"
    },
    {
      "id": "f-advanced-search",
      "enumeration-name": "AdvancedSearch",
      "type": "Feature",
      "module": "Advanced Search",
      "fs-web-rrg": "included",
      "fs-daas-rrg": "included",
      "fs-client-acquisition-b2b-basic": "included",
      "fs-client-acquisition-b2b-advanced": "included",
      "fs-client-acquisition-b2b-daas": "included",
      "fs-client-acquisition-b2c-basic": "included",
      "fs-client-acquisition-b2c-advanced": "included",
      "fs-client-acquisition-b2c-daas": "included",
      "fs-dealmakingpe-basic": "included",
      "fs-dealmakingpe-advanced": "included",
      "fs-dealmakingpe-daas": "included",
      "fs-fundraising-basic": "excluded",
      "fs-fundraising-advanced": "included",
      "fs-fundraising-daas": "included",
      "fs-talent-basic": "excluded",
      "fs-talent-advanced": "included",
      "fs-talent-daas": "included",
      "fs-salesforce-rrg": "included",
      "fs-client-acquisition-b2b-sf": "included",
      "fs-client-acquisition-b2c-sf": "included",
      "fs-dealmakingpe-sf": "included",
      "fs-fundraising-sf": "included",
      "fs-talent-sf": "included"
    },
    {
      "id": "f-modelling",
      "enumeration-name": "Modelling",
      "type": "Feature",
      "module": "Descriptive Modelling / Data Visualization",
      "fs-web-rrg": "included",
      "fs-daas-rrg": "included",
      "fs-client-acquisition-b2b-basic": "excluded",
      "fs-client-acquisition-b2b-advanced": "included",
      "fs-client-acquisition-b2b-daas": "excluded",
      "fs-client-acquisition-b2c-basic": "excluded",
      "fs-client-acquisition-b2c-advanced": "included",
      "fs-client-acquisition-b2c-daas": "excluded",
      "fs-dealmakingpe-basic": "excluded",
      "fs-dealmakingpe-advanced": "included",
      "fs-dealmakingpe-daas": "excluded",
      "fs-fundraising-basic": "excluded",
      "fs-fundraising-advanced": "included",
      "fs-fundraising-daas": "excluded",
      "fs-talent-basic": "excluded",
      "fs-talent-advanced": "included",
      "fs-talent-daas": "excluded",
      "fs-salesforce-rrg": "excluded",
      "fs-client-acquisition-b2b-sf": "excluded",
      "fs-client-acquisition-b2c-sf": "excluded",
      "fs-dealmakingpe-sf": "excluded",
      "fs-fundraising-sf": "excluded",
      "fs-talent-sf": "excluded"
    },
    {
      "id": "f-news-alerts",
      "enumeration-name": "NewsAlerts",
      "type": "Feature",
      "module": "News, Role Change Alerts, News Alerts",
      "fs-web-rrg": "included",
      "fs-daas-rrg": "included",
      "fs-client-acquisition-b2b-basic": "upsell",
      "fs-client-acquisition-b2b-advanced": "upsell",
      "fs-client-acquisition-b2b-daas": "upsell",
      "fs-client-acquisition-b2c-basic": "upsell",
      "fs-client-acquisition-b2c-advanced": "upsell",
      "fs-client-acquisition-b2c-daas": "upsell",
      "fs-dealmakingpe-basic": "upsell",
      "fs-dealmakingpe-advanced": "upsell",
      "fs-dealmakingpe-daas": "upsell",
      "fs-fundraising-basic": "upsell",
      "fs-fundraising-advanced": "upsell",
      "fs-fundraising-daas": "upsell",
      "fs-talent-basic": "upsell",
      "fs-talent-advanced": "upsell",
      "fs-talent-daas": "upsell",
      "fs-salesforce-rrg": "included",
      "fs-client-acquisition-b2b-sf": "upsell",
      "fs-client-acquisition-b2c-sf": "upsell",
      "fs-dealmakingpe-sf": "upsell",
      "fs-fundraising-sf": "upsell",
      "fs-talent-sf": "upsell"
    },
    {
      "id": "f-radar",
      "enumeration-name": "Radar",
      "type": "Feature",
      "module": "Radar",
      "fs-web-rrg": "included",
      "fs-daas-rrg": "included",
      "fs-client-acquisition-b2b-basic": "upsell",
      "fs-client-acquisition-b2b-advanced": "upsell",
      "fs-client-acquisition-b2b-daas": "upsell",
      "fs-client-acquisition-b2c-basic": "upsell",
      "fs-client-acquisition-b2c-advanced": "upsell",
      "fs-client-acquisition-b2c-daas": "upsell",
      "fs-dealmakingpe-basic": "upsell",
      "fs-dealmakingpe-advanced": "upsell",
      "fs-dealmakingpe-daas": "upsell",
      "fs-fundraising-basic": "upsell",
      "fs-fundraising-advanced": "upsell",
      "fs-fundraising-daas": "upsell",
      "fs-talent-basic": "upsell",
      "fs-talent-advanced": "upsell",
      "fs-talent-daas": "upsell",
      "fs-salesforce-rrg": "excluded",
      "fs-client-acquisition-b2b-sf": "excluded",
      "fs-client-acquisition-b2c-sf": "excluded",
      "fs-dealmakingpe-sf": "excluded",
      "fs-fundraising-sf": "excluded",
      "fs-talent-sf": "excluded"
    },
    {
      "id": "f-research-requests",
      "enumeration-name": "ResearchRequests",
      "type": "Feature",
      "module": "Research Requests",
      "fs-web-rrg": "credits",
      "fs-daas-rrg": "credits",
      "fs-client-acquisition-b2b-basic": "credits",
      "fs-client-acquisition-b2b-advanced": "credits",
      "fs-client-acquisition-b2b-daas": "credits",
      "fs-client-acquisition-b2c-basic": "credits",
      "fs-client-acquisition-b2c-advanced": "credits",
      "fs-client-acquisition-b2c-daas": "credits",
      "fs-dealmakingpe-basic": "credits",
      "fs-dealmakingpe-advanced": "credits",
      "fs-dealmakingpe-daas": "credits",
      "fs-fundraising-basic": "credits",
      "fs-fundraising-advanced": "credits",
      "fs-fundraising-daas": "credits",
      "fs-talent-basic": "credits",
      "fs-talent-advanced": "credits",
      "fs-talent-daas": "credits",
      "fs-salesforce-rrg": "credits",
      "fs-client-acquisition-b2b-sf": "credits",
      "fs-client-acquisition-b2c-sf": "credits",
      "fs-dealmakingpe-sf": "credits",
      "fs-fundraising-sf": "credits",
      "fs-talent-sf": "credits"
    },
    {
      "id": "f-diligence",
      "enumeration-name": "Diligence",
      "type": "Feature",
      "module": "Diligence Reports",
      "fs-web-rrg": "credits",
      "fs-daas-rrg": "credits",
      "fs-client-acquisition-b2b-basic": "credits",
      "fs-client-acquisition-b2b-advanced": "credits",
      "fs-client-acquisition-b2b-daas": "credits",
      "fs-client-acquisition-b2c-basic": "credits",
      "fs-client-acquisition-b2c-advanced": "credits",
      "fs-client-acquisition-b2c-daas": "credits",
      "fs-dealmakingpe-basic": "credits",
      "fs-dealmakingpe-advanced": "credits",
      "fs-dealmakingpe-daas": "credits",
      "fs-fundraising-basic": "credits",
      "fs-fundraising-advanced": "credits",
      "fs-fundraising-daas": "credits",
      "fs-talent-basic": "credits",
      "fs-talent-advanced": "credits",
      "fs-talent-daas": "credits",
      "fs-salesforce-rrg": "credits",
      "fs-client-acquisition-b2b-sf": "credits",
      "fs-client-acquisition-b2c-sf": "credits",
      "fs-dealmakingpe-sf": "credits",
      "fs-fundraising-sf": "credits",
      "fs-talent-sf": "credits"
    },
    {
      "id": "f-one-off-reports",
      "enumeration-name": "OneOffReports",
      "type": "Feature",
      "module": "One Off Reports (data exports)",
      "fs-web-rrg": "one_off",
      "fs-daas-rrg": "one_off",
      "fs-client-acquisition-b2b-basic": "one_off",
      "fs-client-acquisition-b2b-advanced": "one_off",
      "fs-client-acquisition-b2b-daas": "one_off",
      "fs-client-acquisition-b2c-basic": "one_off",
      "fs-client-acquisition-b2c-advanced": "one_off",
      "fs-client-acquisition-b2c-daas": "one_off",
      "fs-dealmakingpe-basic": "one_off",
      "fs-dealmakingpe-advanced": "one_off",
      "fs-dealmakingpe-daas": "one_off",
      "fs-fundraising-basic": "one_off",
      "fs-fundraising-advanced": "one_off",
      "fs-fundraising-daas": "one_off",
      "fs-talent-basic": "one_off",
      "fs-talent-advanced": "one_off",
      "fs-talent-daas": "one_off",
      "fs-salesforce-rrg": "one_off",
      "fs-client-acquisition-b2b-sf": "one_off",
      "fs-client-acquisition-b2c-sf": "one_off",
      "fs-dealmakingpe-sf": "one_off",
      "fs-fundraising-sf": "one_off",
      "fs-talent-sf": "one_off"
    },
    {
      "id": "f-in-house-screening",
      "enumeration-name": "InHouseScreening",
      "type": "Feature",
      "module": "In-house Screening",
      "fs-web-rrg": "one_off",
      "fs-daas-rrg": "one_off",
      "fs-client-acquisition-b2b-basic": "one_off",
      "fs-client-acquisition-b2b-advanced": "one_off",
      "fs-client-acquisition-b2b-daas": "one_off",
      "fs-client-acquisition-b2c-basic": "one_off",
      "fs-client-acquisition-b2c-advanced": "one_off",
      "fs-client-acquisition-b2c-daas": "one_off",
      "fs-dealmakingpe-basic": "one_off",
      "fs-dealmakingpe-advanced": "one_off",
      "fs-dealmakingpe-daas": "one_off",
      "fs-fundraising-basic": "one_off",
      "fs-fundraising-advanced": "one_off",
      "fs-fundraising-daas": "one_off",
      "fs-talent-basic": "one_off",
      "fs-talent-advanced": "one_off",
      "fs-talent-daas": "one_off",
      "fs-salesforce-rrg": "one_off",
      "fs-client-acquisition-b2b-sf": "one_off",
      "fs-client-acquisition-b2c-sf": "one_off",
      "fs-dealmakingpe-sf": "one_off",
      "fs-fundraising-sf": "one_off",
      "fs-talent-sf": "one_off"
    }
  ]
}